AUTHORS
MANIFEST.in
README.md
kmodule.c
log.c
setup.py
setuphelp.py
hello-5/Makefile
hello-5/hello-5.c
hello-5/sample.py
kmod/.git
kmod/.gitignore
kmod/.travis.yml
kmod/CODING-STYLE
kmod/COPYING
kmod/Makefile.am
kmod/NEWS
kmod/README
kmod/README.md
kmod/TODO
kmod/autogen.sh
kmod/configure.ac
kmod/libkmod/.gitignore
kmod/libkmod/COPYING
kmod/libkmod/Makefile
kmod/libkmod/README
kmod/libkmod/libkmod-builtin.c
kmod/libkmod/libkmod-config.c
kmod/libkmod/libkmod-elf.c
kmod/libkmod/libkmod-file.c
kmod/libkmod/libkmod-index.c
kmod/libkmod/libkmod-index.h
kmod/libkmod/libkmod-internal.h
kmod/libkmod/libkmod-list.c
kmod/libkmod/libkmod-module.c
kmod/libkmod/libkmod-signature.c
kmod/libkmod/libkmod.c
kmod/libkmod/libkmod.h
kmod/libkmod/libkmod.pc.in
kmod/libkmod/libkmod.sym
kmod/libkmod/docs/.gitignore
kmod/libkmod/docs/Makefile.am
kmod/libkmod/docs/libkmod-docs.xml
kmod/libkmod/docs/libkmod-sections.txt
kmod/libkmod/docs/version.xml.in
kmod/libkmod/python/.gitignore
kmod/libkmod/python/README
kmod/libkmod/python/kmod/__init__.py
kmod/libkmod/python/kmod/_libkmod_h.pxd
kmod/libkmod/python/kmod/_util.pxd
kmod/libkmod/python/kmod/_util.pyx
kmod/libkmod/python/kmod/error.py
kmod/libkmod/python/kmod/kmod.pxd
kmod/libkmod/python/kmod/kmod.pyx
kmod/libkmod/python/kmod/list.pxd
kmod/libkmod/python/kmod/list.pyx
kmod/libkmod/python/kmod/module.pxd
kmod/libkmod/python/kmod/module.pyx
kmod/libkmod/python/kmod/version.py.in
kmod/m4/.gitignore
kmod/m4/attributes.m4
kmod/m4/features.m4
kmod/man/.gitignore
kmod/man/Makefile.am
kmod/man/depmod.d.xml
kmod/man/depmod.xml
kmod/man/insmod.xml
kmod/man/kmod.xml
kmod/man/lsmod.xml
kmod/man/modinfo.xml
kmod/man/modprobe.d.xml
kmod/man/modprobe.xml
kmod/man/modules.dep.xml
kmod/man/rmmod.xml
kmod/shared/.gitignore
kmod/shared/array.c
kmod/shared/array.h
kmod/shared/hash.c
kmod/shared/hash.h
kmod/shared/macro.h
kmod/shared/missing.h
kmod/shared/scratchbuf.c
kmod/shared/scratchbuf.h
kmod/shared/strbuf.c
kmod/shared/strbuf.h
kmod/shared/util.c
kmodule.egg-info/PKG-INFO
kmodule.egg-info/SOURCES.txt
kmodule.egg-info/dependency_links.txt
kmodule.egg-info/top_level.txt