Metadata-Version: 2.1
Name: kmodule
Version: 0.6.0
Summary: Python wrapper for insmod, rmmod, lsmod, modinfo of libkmod
Home-page: https://github.com/EfiPy/kmodule
Author: MaxWu
Author-email: EfiPy.Core@gmail.com
License: GPLv2
Platform: Linux
Classifier: Programming Language :: Python :: 3
Classifier: License :: OSI Approved :: GNU General Public License v2 (GPLv2)
Classifier: Operating System :: POSIX :: Linux
